MTObjectFirstInPython/__init__.py
MTObjectFirstInPython/mainGame.py
MTObjectFirstInPython/mapLoader.py
MTObjectFirstInPython/pgc.py
MTObjectFirstInPython/variablecollector.py
MTObjectFirstInPython-0.0.4.dist-info/DESCRIPTION.rst
MTObjectFirstInPython-0.0.4.dist-info/METADATA
MTObjectFirstInPython-0.0.4.dist-info/RECORD
MTObjectFirstInPython-0.0.4.dist-info/WHEEL
MTObjectFirstInPython-0.0.4.dist-info/metadata.json
MTObjectFirstInPython-0.0.4.dist-info/top_level.txt
