Metadata-Version: 2.0
Name: MTObjectFirstInPython
Version: 0.0.4
Summary: Application of Object First approach for Python using Pygame
Home-page: https://github.com/PaulliDev/MTObjectFirstInPython
Author: Pavol Megela
Author-email: pavol.megela@gmail.com
License: UNKNOWN
Keywords: MTObjectFirstInPython
Platform: UNKNOWN
Classifier: Development Status :: 2 - Pre-Alpha
Classifier: Intended Audience :: Developers
Classifier: Natural Language :: English
Classifier: Programming Language :: Python :: 2
Classifier: Programming Language :: Python :: 2.6
Classifier: Programming Language :: Python :: 2.7
Classifier: Programming Language :: Python :: 3
Classifier: Programming Language :: Python :: 3.3
Classifier: Programming Language :: Python :: 3.4
Classifier: Programming Language :: Python :: 3.5
